Metadata-Version: 1.1
Name: giftoa
Version: 1.0.6.2
Summary: Python script which compiles a native binary that plays a GIF in ASCII on the terminal using ncurses.
Home-page: https://github.com/Teriks/giftoa
Author: Teriks
Author-email: Teriks@users.noreply.github.com
License: BSD 3-Clause
Platform: UNKNOWN
Classifier: Development Status :: 5 - Production/Stable
Classifier: License :: OSI Approved :: BSD License
Classifier: Intended Audience :: End Users/Desktop
Classifier: Natural Language :: English
Classifier: Operating System :: OS Independent
Classifier: Programming Language :: Python :: 3.4
Classifier: Programming Language :: Python :: 3.5
Classifier: Topic :: Artistic Software
Classifier: Topic :: Utilities
